strontium/__init__.py
strontium/cli.py
strontium/medical/augmentations.py
strontium/medical/crop.py
strontium/medical/losses.py
strontium/utils/transforms.py
strontium-0.0.23.dist-info/AUTHORS.rst
strontium-0.0.23.dist-info/LICENSE
strontium-0.0.23.dist-info/METADATA
strontium-0.0.23.dist-info/WHEEL
strontium-0.0.23.dist-info/entry_points.txt
strontium-0.0.23.dist-info/top_level.txt
strontium-0.0.23.dist-info/RECORD
