Metadata-Version: 2.1
Name: strontium
Version: 0.0.23
Summary: strontium is a high-level medical imaging resource for deep learning in Python
Home-page: https://github.com/Trigram19/strontium
Author: Nikhil
Author-email: nikhilpraveen26@gmail.com
License: MIT license
Keywords: strontium
Platform: UNKNOWN
Classifier: Development Status :: 2 - Pre-Alpha
Classifier: Intended Audience :: Developers
Classifier: License :: OSI Approved :: MIT License
Classifier: Natural Language :: English
Classifier: Programming Language :: Python :: 3
Classifier: Programming Language :: Python :: 3.5
Classifier: Programming Language :: Python :: 3.6
Classifier: Programming Language :: Python :: 3.7
Classifier: Programming Language :: Python :: 3.8
Requires-Python: >=3.5
